drift_cli/__init__.py
drift_cli/__main__.py
drift_cli/alias.py
drift_cli/cli.py
drift_cli/config.py
drift_cli/export.py
drift_cli/export_impl/raw.py
drift_cli/utils/__init__.py
drift_cli/utils/consoles.py
drift_cli/utils/error.py
drift_cli/utils/helpers.py
drift_cli/utils/humanize.py
drift_cli-0.10.1.dist-info/LICENSE
drift_cli-0.10.1.dist-info/METADATA
drift_cli-0.10.1.dist-info/WHEEL
drift_cli-0.10.1.dist-info/entry_points.txt
drift_cli-0.10.1.dist-info/top_level.txt
drift_cli-0.10.1.dist-info/RECORD
