Metadata-Version: 2.1
Name: drift-cli
Version: 0.10.1
Summary: CLI client for PANDA | Drift Platform
Author-email: Alexey Timin <atimin@gmail.com>
Maintainer-email: Alexey Timin <atimin@gmail.com>
License: Mozilla Public License Version 2.0
Project-URL: Documentation, https://driftcli.readthedocs.io/en/latest/
Project-URL: SourceCode, https://github.com/panda-official/DriftCLI
Project-URL: Changelog, https://github.com/panda-official/DriftCLI/blob/master/CHANGELOG.md
Project-URL: Blog, https://dev.to/panda-official
Keywords: cli,drift,panda,drift-platform
Classifier: Development Status :: 3 - Alpha
Classifier: Programming Language :: Python :: 3 :: Only
Classifier: Environment :: Console
Classifier: Intended Audience :: Information Technology
Classifier: Intended Audience :: Developers
Classifier: Intended Audience :: System Administrators
Classifier: Operating System :: OS Independent
Classifier: Topic :: Database :: Front-Ends
Requires-Python: >=3.8
License-File: LICENSE
Requires-Dist: drift-python-client ~=0.9.0
Requires-Dist: click ~=8.1
Requires-Dist: tomlkit ~=0.11
Requires-Dist: rich ~=12.6
Provides-Extra: docs
Requires-Dist: mkdocs ~=1.3 ; extra == 'docs'
Requires-Dist: mkdocs-material ~=8.3 ; extra == 'docs'
Requires-Dist: plantuml-markdown ~=3.5 ; extra == 'docs'
Requires-Dist: mkdocs-same-dir ~=0.1 ; extra == 'docs'
Requires-Dist: mkdocs-click ~=0.8 ; extra == 'docs'
Provides-Extra: format
Requires-Dist: black ~=22.6 ; extra == 'format'
Provides-Extra: lint
Requires-Dist: pylint ~=2.14 ; extra == 'lint'
Requires-Dist: pylint-protobuf ==0.20.2 ; extra == 'lint'
Provides-Extra: test
Requires-Dist: pytest ~=7.1 ; extra == 'test'
Requires-Dist: pytest-mock ~=3.10 ; extra == 'test'
Requires-Dist: pytest-asyncio ~=0.18 ; extra == 'test'
